msb/__init__.py
msb/models.py
msb/msb.py
msb/msbdatetime.py
PySchoolBucks-0.2.1.dist-info/LICENSE
PySchoolBucks-0.2.1.dist-info/METADATA
PySchoolBucks-0.2.1.dist-info/WHEEL
PySchoolBucks-0.2.1.dist-info/top_level.txt
PySchoolBucks-0.2.1.dist-info/RECORD
