Metadata-Version: 2.1
Name: PySchoolBucks
Version: 0.2.1
Summary: Python wrapper for the MySchoolBucks Pay API
Home-page: https://github.com/AndrewLester/PySchoolBucks
License: UNKNOWN
Platform: UNKNOWN
Classifier: Programming Language :: Python :: 3
Classifier: License :: OSI Approved :: MIT License
Classifier: Operating System :: OS Independent
Requires-Python: >=3.8
Requires-Dist: requests
